pyautoprocess/__init__.py
pyautoprocess/autoprocess.py
pyautoprocess/batch_reprocess.py
pyautoprocess/image_process.py
pyautoprocess/mrc2tif.py
pyautoprocess/quality_analyzer.py
pyautoprocess/ser2tif.py
pyautoprocess/tvips.py
pyautoprocess/tvips2tif.py
pyautoprocess/config/__init__.py
pyautoprocess/config/config_manager.py
pyautoprocess/config/parameters.py
pyautoprocess/core/__init__.py
pyautoprocess/core/file_handler.py
pyautoprocess/core/process_tracker.py
pyautoprocess/core/xds_manager.py
pyautoprocess/data/bravais_lattices.json
pyautoprocess/data/microscope_configs.json
pyautoprocess/ui/__init__.py
pyautoprocess/ui/cli_parser.py
pyautoprocess/ui/display_manager.py
pyautoprocess/utils/__init__.py
pyautoprocess/workflows/__init__.py
pyautoprocess-0.3.0.dist-info/METADATA
pyautoprocess-0.3.0.dist-info/WHEEL
pyautoprocess-0.3.0.dist-info/entry_points.txt
pyautoprocess-0.3.0.dist-info/licenses/LICENSE
pyautoprocess-0.3.0.dist-info/RECORD
