Metadata-Version: 2.4
Name: pyautoprocess
Version: 0.3.0
Summary: Automated processing and analysis of MicroED data
Project-URL: Homepage, https://github.com/theNelsonLab/autoprocess
Project-URL: Issues, https://github.com/theNelsonLab/autoprocess/issues
Author-email: Dmitry Eremin <eremin@caltech.edu>, Jessica Burch <hosea@caltech.edu>, Sam Foxman <sfoxman@caltech.edu>
License-Expression: GPL-3.0-or-later
License-File: LICENSE
Classifier: Operating System :: OS Independent
Classifier: Programming Language :: Python :: 3
Requires-Python: >=3.8
Requires-Dist: mrcfile~=1.5
Requires-Dist: numpy~=2.0
Requires-Dist: scikit-image>=0.19.0
Requires-Dist: scipy>=1.7.0
Requires-Dist: seremi==0.0.1
Requires-Dist: tifffile>=2025.1.10
Provides-Extra: dev
Requires-Dist: pytest==8.4.2; extra == 'dev'
